COPYING
MANIFEST.in
setup.py
doc/conf.py
nesoni/CHANGES
nesoni/__init__.py
nesoni/__main__.py
nesoni/annotation.py
nesoni/annotation_tools.py
nesoni/bio.py
nesoni/bowtie.py
nesoni/changes.py
nesoni/clip.py
nesoni/config.py
nesoni/consensus.py
nesoni/consequences.py
nesoni/core.py
nesoni/fill_scaffolds.py
nesoni/fisher_diff.py
nesoni/grace.py
nesoni/graph_layout.py
nesoni/igv.py
nesoni/io.py
nesoni/kmer.py
nesoni/legion.py
nesoni/normalize.py
nesoni/nway_diff.py
nesoni/pastiche.py
nesoni/peaks.py
nesoni/recombination.py
nesoni/reference_directory.py
nesoni/reporting.py
nesoni/runr.py
nesoni/sam.py
nesoni/samconsensus.py
nesoni/samcount.py
nesoni/samimport.py
nesoni/samshrimp.py
nesoni/selection.py
nesoni/shred.py
nesoni/shrimp.py
nesoni/span_index.py
nesoni/spanner.py
nesoni/statistics.py
nesoni/storage.py
nesoni/trivia.py
nesoni/variant.py
nesoni/workflows.py
nesoni/working_directory.py
nesoni/workspace.py
nesoni.egg-info/PKG-INFO
nesoni.egg-info/SOURCES.txt
nesoni.egg-info/dependency_links.txt
nesoni.egg-info/entry_points.txt
nesoni.egg-info/pbr.json
nesoni.egg-info/top_level.txt
nesoni/nesoni-r/DESCRIPTION
nesoni/nesoni-r/NAMESPACE
nesoni/nesoni-r/R/basic.R
nesoni/nesoni-r/R/compare.R
nesoni/nesoni-r/R/counts.R
nesoni/nesoni-r/R/fitnoise.R
nesoni/nesoni-r/R/io.R
nesoni/nesoni-r/R/nesoni_version.R
nesoni/nesoni-r/R/nmf.R
nesoni/nesoni-r/R/plotting.R
nesoni/third_party/__init__.py
nesoni/third_party/vcf/__init__.py
nesoni/third_party/vcf/cparse.pyx
nesoni/third_party/vcf/filters.py
nesoni/third_party/vcf/model.py
nesoni/third_party/vcf/parser.py
nesoni/third_party/vcf/utils.py
nesoni/third_party/vcf/test/__init__.py
nesoni/third_party/vcf/test/prof.py
nesoni/third_party/vcf/test/test_vcf.py
treemaker/__init__.py
treemaker/stores.py