Metadata-Version: 1.1
Name: nesoni
Version: 0.132
Summary: Collection of tools for processing high-throughput sequencing data, with an emphasis on bacterial data.
Home-page: http://bioinformatics.net.au/software.nesoni.shtml
Author: Paul Harrison
Author-email: paul.harrison@monash.edu
License: UNKNOWN
Platform: UNKNOWN
Classifier: License :: OSI Approved :: GNU General Public License v2 or later (GPLv2+)
